graphe_circulant/Dijkstra.py
graphe_circulant/Floyd_Warshall.py
graphe_circulant/__init__.py
graphe_circulant/__main__.py
graphe_circulant/circulant_graph.py
graphe_circulant/connexe.py
graphe_circulant/degre.py
graphe_circulant/diametre.py
graphe_circulant/distance.py
graphe_circulant/formulDiam.py
graphe_circulant/interface.py
graphe_circulant/parcours.py
graphe_circulant/plus_court_chemin.py
graphe_circulant/assets/frame0/button_1.png
graphe_circulant/assets/frame0/button_2.png
graphe_circulant/assets/frame0/button_3.png
graphe_circulant/assets/frame0/button_4.png
graphe_circulant/assets/frame0/button_5.png
graphe_circulant/assets/frame0/button_6.png
graphe_circulant/assets/frame0/button_7.png
graphe_circulant/assets/frame0/entry_1.png
graphe_circulant/assets/frame0/entry_2.png
graphe_circulant/assets/frame0/image_1.png
graphe_circulant/assets/frame0/image_2.png
graphe_circulant/assets/frame0/image_21.png
graphe_circulant/assets/frame0/image_3.png
graphe_circulant/assets/frame0/image_4.png
graphe_circulant/assets/frame0/image_5.png
graphe_circulant-0.1.9.dist-info/METADATA
graphe_circulant-0.1.9.dist-info/WHEEL
graphe_circulant-0.1.9.dist-info/entry_points.txt
graphe_circulant-0.1.9.dist-info/top_level.txt
graphe_circulant-0.1.9.dist-info/RECORD
