Metadata-Version: 2.4
Name: graphe_circulant
Version: 0.1.9
Summary: Package pour le calcul de diamètres de graphes circulants
Author: lakrakar_labibi
Author-email: lakrakarouafaa@email.com
Classifier: Programming Language :: Python :: 3
Classifier: License :: OSI Approved :: MIT License
Classifier: Operating System :: OS Independent
Requires-Python: >=3.7
Requires-Dist: matplotlib
Requires-Dist: numpy
Requires-Dist: customtkinter
Dynamic: author
Dynamic: author-email
Dynamic: classifier
Dynamic: description-content-type
Dynamic: requires-dist
Dynamic: requires-python
Dynamic: summary
